xftOpenApi/SM2.py
xftOpenApi/SM3.py
xftOpenApi/__init__.py
xftOpenApi/main.py
xftOpenApi/openAPI.py
xftOpenApi/test.py
xftOpenApi/xft_open_api.py
xftOpenApi-1.0.0.dist-info/LICENSE
xftOpenApi-1.0.0.dist-info/METADATA
xftOpenApi-1.0.0.dist-info/WHEEL
xftOpenApi-1.0.0.dist-info/top_level.txt
xftOpenApi-1.0.0.dist-info/RECORD
