Metadata-Version: 2.1
Name: xftOpenApi
Version: 1.0.0
Summary: 薪福通API接口SDK
Home-page: https://gitee.com/Muzi-Li-Chine/xftOpenApi.git
Author: 木子李
Author-email: 1537080775@qq.com
Classifier: Programming Language :: Python :: 3
Classifier: License :: OSI Approved :: MIT License
Classifier: Operating System :: OS Independent
Requires-Python: >=3.6, <4
License-File: LICENSE
Requires-Dist: gmssl>=3.2.2
